{
  "@xsi:type": "OrganeCirconscription_type",
  "uid": "PO230887",
  "codeType": "CIRCONSCRIPTION",
  "libelle": "4ème circonscription des Deux-Sèvres",
  "libelleEdition": "de la circonscription",
  "libelleAbrege": "79 Deux-Sèvres (° 4°)",
  "libelleAbrev": "CIRCO",
  "viMoDe": {
    "dateDebut": "2002-06-19",
    "dateAgrement": null,
    "dateFin": "2007-06-19"
  },
  "organeParent": null,
  "chambre": null,
  "regime": "5ème République",
  "legislature": "12",
  "numero": "4",
  "lieu": {
    "region": {
      "type": "Métropolitain",
      "libelle": "Nouvelle-Aquitaine"
    },
    "departement": {
      "codeNatureDep": "M",
      "code": "79",
      "libelle": "Deux-Sèvres"
    }
  }
}