{
  "uid": {
    "@xsi:type": "IdActeur_type",
    "#text": "PA343034"
  },
  "etatCivil": {
    "ident": {
      "civ": "M.",
      "prenom": "Paul",
      "nom": "Jeanneteau",
      "alpha": "Jeanneteau",
      "trigramme": {
        "@xsi:nil": "true"
      }
    },
    "infoNaissance": {
      "dateNais": "1957-10-14",
      "villeNais": "Angers",
      "depNais": "Maine-et-Loire",
      "paysNais": "France"
    },
    "dateDeces": {
      "@xsi:nil": "true"
    }
  },
  "profession": {
    "libelleCourant": "Pharmacien d'officine",
    "socProcINSEE": {
      "catSocPro": "Professions libérales et assimilés",
      "famSocPro": "Cadres et professions intellectuelles supérieures"
    }
  },
  "uri_hatvp": {
    "@xsi:nil": "true"
  },
  "adresses": {
    "adresse": [
      {
        "@xsi:type": "AdressePostale_Type",
        "uid": "AD392604",
        "type": "0",
        "typeLibelle": "Adresse officielle",
        "poids": "1",
        "adresseDeRattachement": null,
        "intitule": "Assemblée nationale,",
        "numeroRue": "126",
        "nomRue": "Rue de l'Université,",
        "complementAdresse": null,
        "codePostal": "75355",
        "ville": "Paris 07 SP"
      },
      {
        "@xsi:type": "AdresseMail_Type",
        "uid": "AD394353",
        "type": "15",
        "typeLibelle": "Mèl",
        "poids": null,
        "adresseDeRattachement": null,
        "valElec": "pjeanneteau@assemblee-nationale.fr"
      }
    ]
  },
  "mandats": {
    "mandat": [
      {
        "@xsi:type": "MandatMission_Type",
        "uid": "PM414651",
        "acteurRef": "PA343034",
        "legislature": "13",
        "typeOrgane": "MISINFOPRE",
        "dateDebut": "2008-07-09",
        "datePublication": "2008-07-10",
        "dateFin": "2010-01-22",
        "preseance": "20",
        "nominPrincipale": "1",
        "infosQualite": {
          "codeQualite": "Membre",
          "libQualite": "Membre",
          "libQualiteSex": "Membre"
        },
        "organes": {
          "organeRef": "PO414626"
        },
        "libelle": null,
        "missionSuivanteRef": null,
        "missionPrecedenteRef": null
      },
      {
        "@xsi:type": "MandatSimple_Type",
        "uid": "PM425660",
        "acteurRef": "PA343034",
        "legislature": "13",
        "typeOrgane": "CNPS",
        "dateDebut": "2010-11-10",
        "datePublication": "2010-11-11",
        "dateFin": "2011-06-23",
        "preseance": "20",
        "nominPrincipale": "1",
        "infosQualite": {
          "codeQualite": "Membre",
          "libQualite": "Membre",
          "libQualiteSex": "Membre"
        },
        "organes": {
          "organeRef": "PO425550"
        }
      },
      {
        "@xsi:type": "MandatSimple_Type",
        "uid": "PM423405",
        "acteurRef": "PA343034",
        "legislature": "13",
        "typeOrgane": "CNPE",
        "dateDebut": "2010-03-30",
        "datePublication": "2010-03-31",
        "dateFin": "2010-03-30",
        "preseance": "20",
        "nominPrincipale": "1",
        "infosQualite": {
          "codeQualite": "Membre",
          "libQualite": "Membre",
          "libQualiteSex": "Membre"
        },
        "organes": {
          "organeRef": "PO423145"
        }
      },
      {
        "@xsi:type": "MandatSimple_Type",
        "uid": "PM393603",
        "acteurRef": "PA343034",
        "legislature": "13",
        "typeOrgane": "GP",
        "dateDebut": "2007-07-24",
        "datePublication": "2007-07-24",
        "dateFin": "2012-06-16",
        "preseance": "20",
        "nominPrincipale": "1",
        "infosQualite": {
          "codeQualite": "Membre",
          "libQualite": "Membre du",
          "libQualiteSex": "Membre du"
        },
        "organes": {
          "organeRef": "PO389395"
        }
      },
      {
        "@xsi:type": "MandatSimple_Type",
        "uid": "PM394013",
        "acteurRef": "PA343034",
        "legislature": "13",
        "typeOrgane": "COMPER",
        "dateDebut": "2007-07-27",
        "datePublication": "2007-07-28",
        "dateFin": "2009-06-30",
        "preseance": "32",
        "nominPrincipale": "1",
        "infosQualite": {
          "codeQualite": "Membre",
          "libQualite": "Membre",
          "libQualiteSex": "Membre"
        },
        "organes": {
          "organeRef": "PO59045"
        }
      },
      {
        "@xsi:type": "MandatSimple_Type",
        "uid": "PM420500",
        "acteurRef": "PA343034",
        "legislature": "13",
        "typeOrgane": "COMPER",
        "dateDebut": "2009-07-01",
        "datePublication": "2009-07-01",
        "dateFin": "2012-06-16",
        "preseance": "32",
        "nominPrincipale": "1",
        "infosQualite": {
          "codeQualite": "Membre",
          "libQualite": "Membre",
          "libQualiteSex": "Membre"
        },
        "organes": {
          "organeRef": "PO420120"
        }
      },
      {
        "@xsi:type": "MandatSimple_Type",
        "uid": "PM428808",
        "acteurRef": "PA343034",
        "legislature": "13",
        "typeOrgane": "CMP",
        "dateDebut": "2011-06-14",
        "datePublication": "2011-06-15",
        "dateFin": "2011-07-25",
        "preseance": "20",
        "nominPrincipale": "1",
        "infosQualite": {
          "codeQualite": "Titulaire",
          "libQualite": "Membre titulaire",
          "libQualiteSex": "Membre titulaire"
        },
        "organes": {
          "organeRef": "PO428784"
        }
      },
      {
        "@xsi:type": "MandatSimple_Type",
        "uid": "PM425852",
        "acteurRef": "PA343034",
        "legislature": "13",
        "typeOrgane": "CNPS",
        "dateDebut": "2010-11-17",
        "datePublication": "2010-11-18",
        "dateFin": "2011-06-23",
        "preseance": "8",
        "nominPrincipale": "1",
        "infosQualite": {
          "codeQualite": "Vice-Président",
          "libQualite": "Vice-Président",
          "libQualiteSex": "Vice-Président"
        },
        "organes": {
          "organeRef": "PO425550"
        }
      },
      {
        "@xsi:type": "MandatSimple_Type",
        "uid": "PM410883",
        "acteurRef": "PA343034",
        "legislature": "13",
        "typeOrgane": "GE",
        "dateDebut": "2008-01-08",
        "datePublication": null,
        "dateFin": "2012-06-16",
        "preseance": "20",
        "nominPrincipale": "1",
        "infosQualite": {
          "codeQualite": "Membre",
          "libQualite": "Membre",
          "libQualiteSex": "Membre"
        },
        "organes": {
          "organeRef": "PO402919"
        }
      },
      {
        "@xsi:type": "MandatSimple_Type",
        "uid": "PM421987",
        "acteurRef": "PA343034",
        "legislature": "13",
        "typeOrgane": "GE",
        "dateDebut": "2007-10-31",
        "datePublication": null,
        "dateFin": "2012-06-16",
        "preseance": "20",
        "nominPrincipale": "1",
        "infosQualite": {
          "codeQualite": "Membre",
          "libQualite": "Membre",
          "libQualiteSex": "Membre"
        },
        "organes": {
          "organeRef": "PO403063"
        }
      },
      {
        "@xsi:type": "MandatSimple_Type",
        "uid": "PM406834",
        "acteurRef": "PA343034",
        "legislature": "13",
        "typeOrgane": "GE",
        "dateDebut": "2008-01-15",
        "datePublication": null,
        "dateFin": "2012-06-16",
        "preseance": "20",
        "nominPrincipale": "1",
        "infosQualite": {
          "codeQualite": "Membre",
          "libQualite": "Membre",
          "libQualiteSex": "Membre"
        },
        "organes": {
          "organeRef": "PO402734"
        }
      },
      {
        "@xsi:type": "MandatSimple_Type",
        "uid": "PM398281",
        "acteurRef": "PA343034",
        "legislature": "13",
        "typeOrgane": "GA",
        "dateDebut": "2007-10-11",
        "datePublication": null,
        "dateFin": "2012-06-16",
        "preseance": "20",
        "nominPrincipale": "1",
        "infosQualite": {
          "codeQualite": "Membre",
          "libQualite": "Membre",
          "libQualiteSex": "Membre"
        },
        "organes": {
          "organeRef": "PO393035"
        }
      },
      {
        "@xsi:type": "MandatSimple_Type",
        "uid": "PM398283",
        "acteurRef": "PA343034",
        "legislature": "13",
        "typeOrgane": "GA",
        "dateDebut": "2007-10-11",
        "datePublication": null,
        "dateFin": "2012-06-16",
        "preseance": "20",
        "nominPrincipale": "1",
        "infosQualite": {
          "codeQualite": "Membre",
          "libQualite": "Membre",
          "libQualiteSex": "Membre"
        },
        "organes": {
          "organeRef": "PO393338"
        }
      },
      {
        "@xsi:type": "MandatSimple_Type",
        "uid": "PM398282",
        "acteurRef": "PA343034",
        "legislature": "13",
        "typeOrgane": "GA",
        "dateDebut": "2007-10-11",
        "datePublication": null,
        "dateFin": "2012-06-16",
        "preseance": "20",
        "nominPrincipale": "1",
        "infosQualite": {
          "codeQualite": "Membre",
          "libQualite": "Membre",
          "libQualiteSex": "Membre"
        },
        "organes": {
          "organeRef": "PO393308"
        }
      },
      {
        "@xsi:type": "MandatSimple_Type",
        "uid": "PM398284",
        "acteurRef": "PA343034",
        "legislature": "13",
        "typeOrgane": "GA",
        "dateDebut": "2007-10-11",
        "datePublication": null,
        "dateFin": "2012-06-16",
        "preseance": "20",
        "nominPrincipale": "1",
        "infosQualite": {
          "codeQualite": "Membre",
          "libQualite": "Membre",
          "libQualiteSex": "Membre"
        },
        "organes": {
          "organeRef": "PO393343"
        }
      },
      {
        "@xsi:type": "MandatSimple_Type",
        "uid": "PM392620",
        "acteurRef": "PA343034",
        "legislature": "13",
        "typeOrgane": "GP",
        "dateDebut": "2007-07-20",
        "datePublication": "2007-07-21",
        "dateFin": "2007-07-23",
        "preseance": "28",
        "nominPrincipale": "1",
        "infosQualite": {
          "codeQualite": "Député non-inscrit",
          "libQualite": "Député non-inscrit",
          "libQualiteSex": "Député non-inscrit"
        },
        "organes": {
          "organeRef": "PO387155"
        }
      },
      {
        "@xsi:type": "MandatSimple_Type",
        "uid": "PM408300",
        "acteurRef": "PA343034",
        "legislature": "13",
        "typeOrgane": "GE",
        "dateDebut": "2008-02-05",
        "datePublication": null,
        "dateFin": "2012-06-16",
        "preseance": "8",
        "nominPrincipale": "1",
        "infosQualite": {
          "codeQualite": "Vice-Président",
          "libQualite": "Vice-Président",
          "libQualiteSex": "Vice-Président"
        },
        "organes": {
          "organeRef": "PO402734"
        }
      },
      {
        "@xsi:type": "MandatParlementaire_type",
        "uid": "PM392585",
        "acteurRef": "PA343034",
        "legislature": "13",
        "typeOrgane": "ASSEMBLEE",
        "dateDebut": "2007-06-20",
        "datePublication": null,
        "dateFin": "2012-06-16",
        "preseance": "50",
        "nominPrincipale": "1",
        "infosQualite": {
          "codeQualite": "membre",
          "libQualite": "membre",
          "libQualiteSex": "membre"
        },
        "organes": {
          "organeRef": "PO384266"
        },
        "suppleants": null,
        "chambre": null,
        "election": {
          "lieu": {
            "region": "Pays de la Loire",
            "regionType": "Métropolitain",
            "departement": "Maine-et-Loire",
            "numDepartement": "49",
            "numCirco": "1"
          },
          "causeMandat": "remplacement d'un député nommé au Gouvernement",
          "refCirconscription": "PO384492"
        },
        "mandature": {
          "datePriseFonction": "2007-07-20",
          "causeFin": "Reprise de l'exercice du mandat d'un ancien membre du Gouvernement",
          "premiereElection": "0",
          "placeHemicycle": null,
          "mandatRemplaceRef": null
        },
        "collaborateurs": null
      }
    ]
  }
}