{
  "uid": {
    "@xsi:type": "IdActeur_type",
    "#text": "PA693008"
  },
  "etatCivil": {
    "ident": {
      "civ": "M.",
      "prenom": "Napole",
      "nom": "Polutele",
      "alpha": "Polutele",
      "trigramme": {
        "@xsi:nil": "true"
      }
    },
    "infoNaissance": {
      "dateNais": "1964-06-25",
      "villeNais": "Mua",
      "depNais": "Wallis-et-Futuna",
      "paysNais": "France"
    },
    "dateDeces": {
      "@xsi:nil": "true"
    }
  },
  "profession": {
    "libelleCourant": "Professeur d'histoire-géographie",
    "socProcINSEE": {
      "catSocPro": "Cadres de la fonction publique, professions intellectuelles et  artistiques",
      "famSocPro": "Cadres et professions intellectuelles supérieures"
    }
  },
  "uri_hatvp": {
    "@xsi:nil": "true"
  },
  "adresses": {
    "adresse": [
      {
        "@xsi:type": "AdressePostale_Type",
        "uid": "AD693011",
        "type": "0",
        "typeLibelle": "Adresse officielle",
        "poids": "1",
        "adresseDeRattachement": null,
        "intitule": "Assemblée nationale",
        "numeroRue": "126",
        "nomRue": "Rue de l'Université",
        "complementAdresse": null,
        "codePostal": "75355",
        "ville": "Paris 07 SP"
      },
      {
        "@xsi:type": "AdresseMail_Type",
        "uid": "AD716622",
        "type": "15",
        "typeLibelle": "Mèl",
        "poids": null,
        "adresseDeRattachement": null,
        "valElec": "napole.polutele@assemblee-nationale.fr"
      }
    ]
  },
  "mandats": {
    "mandat": [
      {
        "@xsi:type": "MandatSimple_Type",
        "uid": "PM732553",
        "acteurRef": "PA693008",
        "legislature": "15",
        "typeOrgane": "DELEG",
        "dateDebut": "2017-07-12",
        "datePublication": "2017-07-12",
        "dateFin": "2018-02-02",
        "preseance": "20",
        "nominPrincipale": "1",
        "infosQualite": {
          "codeQualite": "Membre",
          "libQualite": "Membre",
          "libQualiteSex": "Membre"
        },
        "organes": {
          "organeRef": "PO675659"
        }
      },
      {
        "@xsi:type": "MandatSimple_Type",
        "uid": "PM695377",
        "acteurRef": "PA693008",
        "legislature": "14",
        "typeOrgane": "DELEG",
        "dateDebut": "2013-03-24",
        "datePublication": "2013-03-25",
        "dateFin": "2017-06-20",
        "preseance": "20",
        "nominPrincipale": "1",
        "infosQualite": {
          "codeQualite": "Membre",
          "libQualite": "Membre",
          "libQualiteSex": "Membre"
        },
        "organes": {
          "organeRef": "PO675659"
        }
      },
      {
        "@xsi:type": "MandatMission_Type",
        "uid": "PM704529",
        "acteurRef": "PA693008",
        "legislature": "14",
        "typeOrgane": "MISINFOPRE",
        "dateDebut": "2014-11-06",
        "datePublication": "2014-11-07",
        "dateFin": "2017-03-28",
        "preseance": "20",
        "nominPrincipale": "1",
        "infosQualite": {
          "codeQualite": "Membre",
          "libQualite": "Membre",
          "libQualiteSex": "Membre"
        },
        "organes": {
          "organeRef": "PO703871"
        },
        "libelle": null,
        "missionSuivanteRef": null,
        "missionPrecedenteRef": null
      },
      {
        "@xsi:type": "MandatSimple_Type",
        "uid": "PM746031",
        "acteurRef": "PA693008",
        "legislature": null,
        "typeOrgane": "PARPOL",
        "dateDebut": "2017-12-01",
        "datePublication": null,
        "dateFin": "2018-11-30",
        "preseance": "5",
        "nominPrincipale": "1",
        "infosQualite": {
          "codeQualite": "Membre",
          "libQualite": "Membre",
          "libQualiteSex": "Membre"
        },
        "organes": {
          "organeRef": "PO744864"
        }
      },
      {
        "@xsi:type": "MandatSimple_Type",
        "uid": "PM739157",
        "acteurRef": "PA693008",
        "legislature": "15",
        "typeOrgane": "GEVI",
        "dateDebut": "2017-10-11",
        "datePublication": null,
        "dateFin": "2017-11-07",
        "preseance": "20",
        "nominPrincipale": "1",
        "infosQualite": {
          "codeQualite": "Membre",
          "libQualite": "Membre",
          "libQualiteSex": "Membre"
        },
        "organes": {
          "organeRef": "PO733688"
        }
      },
      {
        "@xsi:type": "MandatSimple_Type",
        "uid": "PM704826",
        "acteurRef": "PA693008",
        "legislature": null,
        "typeOrgane": "PARPOL",
        "dateDebut": "2013-12-01",
        "datePublication": null,
        "dateFin": "2017-06-20",
        "preseance": "5",
        "nominPrincipale": "1",
        "infosQualite": {
          "codeQualite": "Membre",
          "libQualite": "Membre",
          "libQualiteSex": "Membre"
        },
        "organes": {
          "organeRef": "PO684932"
        }
      },
      {
        "@xsi:type": "MandatSimple_Type",
        "uid": "PM743876",
        "acteurRef": "PA693008",
        "legislature": "15",
        "typeOrgane": "GEVI",
        "dateDebut": "2017-11-08",
        "datePublication": null,
        "dateFin": "2018-02-02",
        "preseance": "20",
        "nominPrincipale": "1",
        "infosQualite": {
          "codeQualite": "Membre",
          "libQualite": "Membre",
          "libQualiteSex": "Membre"
        },
        "organes": {
          "organeRef": "PO743840"
        }
      },
      {
        "@xsi:type": "MandatSimple_Type",
        "uid": "PM695378",
        "acteurRef": "PA693008",
        "legislature": "14",
        "typeOrgane": "DELEG",
        "dateDebut": "2013-03-24",
        "datePublication": "2013-03-25",
        "dateFin": "2017-06-20",
        "preseance": "21",
        "nominPrincipale": "0",
        "infosQualite": {
          "codeQualite": "Membre de droit",
          "libQualite": "Membre de droit",
          "libQualiteSex": "Membre de droit"
        },
        "organes": {
          "organeRef": "PO675659"
        }
      },
      {
        "@xsi:type": "MandatSimple_Type",
        "uid": "PM693700",
        "acteurRef": "PA693008",
        "legislature": "14",
        "typeOrgane": "COMPER",
        "dateDebut": "2013-04-16",
        "datePublication": "2013-04-16",
        "dateFin": "2017-06-20",
        "preseance": "32",
        "nominPrincipale": "1",
        "infosQualite": {
          "codeQualite": "Membre",
          "libQualite": "Membre",
          "libQualiteSex": "Membre"
        },
        "organes": {
          "organeRef": "PO419865"
        }
      },
      {
        "@xsi:type": "MandatSimple_Type",
        "uid": "PM746340",
        "acteurRef": "PA693008",
        "legislature": "15",
        "typeOrgane": "COMPER",
        "dateDebut": "2017-12-13",
        "datePublication": "2017-12-13",
        "dateFin": "2018-02-02",
        "preseance": "32",
        "nominPrincipale": "1",
        "infosQualite": {
          "codeQualite": "Membre",
          "libQualite": "Membre",
          "libQualiteSex": "Membre"
        },
        "organes": {
          "organeRef": "PO419865"
        }
      },
      {
        "@xsi:type": "MandatSimple_Type",
        "uid": "PM743615",
        "acteurRef": "PA693008",
        "legislature": "15",
        "typeOrgane": "COMPER",
        "dateDebut": "2017-11-22",
        "datePublication": "2017-11-22",
        "dateFin": "2017-12-12",
        "preseance": "32",
        "nominPrincipale": "1",
        "infosQualite": {
          "codeQualite": "Membre",
          "libQualite": "Membre",
          "libQualiteSex": "Membre"
        },
        "organes": {
          "organeRef": "PO59048"
        }
      },
      {
        "@xsi:type": "MandatSimple_Type",
        "uid": "PM731767",
        "acteurRef": "PA693008",
        "legislature": "15",
        "typeOrgane": "COMPER",
        "dateDebut": "2017-06-29",
        "datePublication": "2017-06-29",
        "dateFin": "2017-11-21",
        "preseance": "32",
        "nominPrincipale": "1",
        "infosQualite": {
          "codeQualite": "Membre",
          "libQualite": "Membre",
          "libQualiteSex": "Membre"
        },
        "organes": {
          "organeRef": "PO419865"
        }
      },
      {
        "@xsi:type": "MandatSimple_Type",
        "uid": "PM697293",
        "acteurRef": "PA693008",
        "legislature": "14",
        "typeOrgane": "GE",
        "dateDebut": "2013-10-01",
        "datePublication": null,
        "dateFin": "2017-06-20",
        "preseance": "20",
        "nominPrincipale": "1",
        "infosQualite": {
          "codeQualite": "Membre",
          "libQualite": "Membre",
          "libQualiteSex": "Membre"
        },
        "organes": {
          "organeRef": "PO694560"
        }
      },
      {
        "@xsi:type": "MandatSimple_Type",
        "uid": "PM739154",
        "acteurRef": "PA693008",
        "legislature": "15",
        "typeOrgane": "GA",
        "dateDebut": "2017-10-11",
        "datePublication": null,
        "dateFin": "2018-02-02",
        "preseance": "20",
        "nominPrincipale": "1",
        "infosQualite": {
          "codeQualite": "Membre",
          "libQualite": "Membre",
          "libQualiteSex": "Membre"
        },
        "organes": {
          "organeRef": "PO733242"
        }
      },
      {
        "@xsi:type": "MandatSimple_Type",
        "uid": "PM724631",
        "acteurRef": "PA693008",
        "legislature": "15",
        "typeOrgane": "GP",
        "dateDebut": "2017-06-21",
        "datePublication": null,
        "dateFin": "2017-06-26",
        "preseance": "28",
        "nominPrincipale": "1",
        "infosQualite": {
          "codeQualite": "Député non-inscrit",
          "libQualite": "Député non-inscrit",
          "libQualiteSex": "Député non-inscrit"
        },
        "organes": {
          "organeRef": "PO723569"
        }
      },
      {
        "@xsi:type": "MandatSimple_Type",
        "uid": "PM694962",
        "acteurRef": "PA693008",
        "legislature": "14",
        "typeOrgane": "GP",
        "dateDebut": "2013-05-31",
        "datePublication": "2013-06-01",
        "dateFin": "2016-05-24",
        "preseance": "24",
        "nominPrincipale": "1",
        "infosQualite": {
          "codeQualite": "Membre apparenté",
          "libQualite": "Apparenté au",
          "libQualiteSex": "Apparenté au"
        },
        "organes": {
          "organeRef": "PO656002"
        }
      },
      {
        "@xsi:type": "MandatSimple_Type",
        "uid": "PM744429",
        "acteurRef": "PA693008",
        "legislature": "15",
        "typeOrgane": "GP",
        "dateDebut": "2017-11-29",
        "datePublication": null,
        "dateFin": "2018-02-02",
        "preseance": "24",
        "nominPrincipale": "1",
        "infosQualite": {
          "codeQualite": "Membre apparenté",
          "libQualite": "Apparenté au",
          "libQualiteSex": "Apparenté au"
        },
        "organes": {
          "organeRef": "PO744425"
        }
      },
      {
        "@xsi:type": "MandatSimple_Type",
        "uid": "PM693016",
        "acteurRef": "PA693008",
        "legislature": "14",
        "typeOrgane": "GP",
        "dateDebut": "2013-03-24",
        "datePublication": null,
        "dateFin": "2013-05-31",
        "preseance": "28",
        "nominPrincipale": "1",
        "infosQualite": {
          "codeQualite": "Député non-inscrit",
          "libQualite": "Député non-inscrit",
          "libQualiteSex": "Député non-inscrit"
        },
        "organes": {
          "organeRef": "PO645633"
        }
      },
      {
        "@xsi:type": "MandatSimple_Type",
        "uid": "PM731478",
        "acteurRef": "PA693008",
        "legislature": "15",
        "typeOrgane": "GP",
        "dateDebut": "2017-06-27",
        "datePublication": "2017-06-28",
        "dateFin": "2017-11-28",
        "preseance": "24",
        "nominPrincipale": "1",
        "infosQualite": {
          "codeQualite": "Membre apparenté",
          "libQualite": "Apparenté au",
          "libQualiteSex": "Apparenté au"
        },
        "organes": {
          "organeRef": "PO730952"
        }
      },
      {
        "@xsi:type": "MandatSimple_Type",
        "uid": "PM713371",
        "acteurRef": "PA693008",
        "legislature": "14",
        "typeOrgane": "GP",
        "dateDebut": "2016-05-25",
        "datePublication": null,
        "dateFin": "2017-06-20",
        "preseance": "24",
        "nominPrincipale": "1",
        "infosQualite": {
          "codeQualite": "Membre apparenté",
          "libQualite": "Apparenté au",
          "libQualiteSex": "Apparenté au"
        },
        "organes": {
          "organeRef": "PO713077"
        }
      },
      {
        "@xsi:type": "MandatParlementaire_type",
        "uid": "PM693014",
        "acteurRef": "PA693008",
        "legislature": "14",
        "typeOrgane": "ASSEMBLEE",
        "dateDebut": "2013-03-24",
        "datePublication": null,
        "dateFin": "2017-06-20",
        "preseance": "50",
        "nominPrincipale": "1",
        "infosQualite": {
          "codeQualite": "membre",
          "libQualite": "membre",
          "libQualiteSex": "membre"
        },
        "organes": {
          "organeRef": "PO644420"
        },
        "suppleants": null,
        "chambre": null,
        "election": {
          "lieu": {
            "region": "Wallis-et-Futuna",
            "regionType": "Collectivités d'outre-mer et Nouvelle-Calédonie",
            "departement": "Wallis-et-Futuna",
            "numDepartement": "986",
            "numCirco": "1"
          },
          "causeMandat": "élection partielle, suite à l'annulation de l'élection d'un député",
          "refCirconscription": "PO644993"
        },
        "mandature": {
          "datePriseFonction": "2013-03-24",
          "causeFin": "Fin de législature",
          "premiereElection": "0",
          "placeHemicycle": null,
          "mandatRemplaceRef": null
        },
        "collaborateurs": null
      },
      {
        "@xsi:type": "MandatParlementaire_type",
        "uid": "PM723180",
        "acteurRef": "PA693008",
        "legislature": "15",
        "typeOrgane": "ASSEMBLEE",
        "dateDebut": "2017-06-11",
        "datePublication": null,
        "dateFin": "2018-02-02",
        "preseance": "50",
        "nominPrincipale": "1",
        "infosQualite": {
          "codeQualite": "membre",
          "libQualite": "membre",
          "libQualiteSex": "membre"
        },
        "organes": {
          "organeRef": "PO717460"
        },
        "suppleants": {
          "suppleant": {
            "dateDebut": "2017-06-11",
            "dateFin": "2018-02-02",
            "suppleantRef": "PA717375"
          }
        },
        "chambre": null,
        "election": {
          "lieu": {
            "region": "Wallis-et-Futuna",
            "regionType": "Collectivités d'outre-mer et Nouvelle-Calédonie",
            "departement": "Wallis-et-Futuna",
            "numDepartement": "986",
            "numCirco": "1"
          },
          "causeMandat": "élections générales",
          "refCirconscription": "PO718554"
        },
        "mandature": {
          "datePriseFonction": "2017-06-21",
          "causeFin": "Annulation de l'élection sur décision du Conseil constitutionnel",
          "premiereElection": "1",
          "placeHemicycle": null,
          "mandatRemplaceRef": null
        },
        "collaborateurs": null
      }
    ]
  }
}