{
  "@xsi:type": "OrganeParlementaire_Type",
  "uid": "PO773071",
  "codeType": "MISINFO",
  "libelle": "Problématiques de sécurité associées à la présence de mineurs non accompagnés",
  "libelleEdition": "de la mission d'information sur les problématiques de sécurité associées à la présence sur le territoire de mineurs non accompagnés",
  "libelleAbrege": "Problématiques de sécurité associées à la présence de mineurs non accompagnés",
  "libelleAbrev": "SECURMNA",
  "viMoDe": {
    "dateDebut": "2020-07-01",
    "dateAgrement": null,
    "dateFin": "2021-03-11"
  },
  "organeParent": null,
  "chambre": null,
  "regime": "5ème République",
  "legislature": "15",
  "secretariat": {
    "secretaire01": null,
    "secretaire02": null
  }
}