{
  "@xsi:type": "OrganeParlementaire_Type",
  "uid": "PO804107",
  "codeType": "MISINFO",
  "libelle": "Mission d'évaluation et de contrôle des lois de financement de la sécurité sociale",
  "libelleEdition": "de la mission d'évaluation et de contrôle des lois de financement de la sécurité sociale",
  "libelleAbrege": "MEC Sécurité sociale",
  "libelleAbrev": "MECSS",
  "viMoDe": {
    "dateDebut": "2022-08-02",
    "dateAgrement": null,
    "dateFin": null
  },
  "organeParent": "PO420120",
  "chambre": null,
  "regime": "5ème République",
  "legislature": "16",
  "secretariat": {
    "secretaire01": null,
    "secretaire02": null
  }
}