{
  "uid": {
    "@xsi:type": "IdActeur_type",
    "#text": "PA796062"
  },
  "etatCivil": {
    "ident": {
      "civ": "M.",
      "prenom": "Thomas",
      "nom": "Portes",
      "alpha": "Portes",
      "trigramme": "TPO"
    },
    "infoNaissance": {
      "dateNais": "1985-11-18",
      "villeNais": "Carmaux",
      "depNais": "Tarn",
      "paysNais": "France"
    }
  },
  "profession": {
    "libelleCourant": "Cheminot",
    "socProcINSEE": {
      "catSocPro": "Employés de la fonction publique",
      "famSocPro": "Employés"
    }
  },
  "uri_hatvp": "https://www.hatvp.fr/pages_nominatives/portes-thomas-24240",
  "adresses": {
    "adresse": [
      {
        "@xsi:type": "AdressePostale_Type",
        "uid": "AD796064",
        "type": "0",
        "typeLibelle": "Adresse officielle",
        "poids": "1",
        "adresseDeRattachement": null,
        "intitule": "Assemblée nationale,",
        "numeroRue": "126",
        "nomRue": "Rue de l'Université,",
        "complementAdresse": null,
        "codePostal": "75355",
        "ville": "Paris 07 SP"
      },
      {
        "@xsi:type": "AdresseMail_Type",
        "uid": "AD798129",
        "type": "15",
        "typeLibelle": "Mèl",
        "poids": null,
        "adresseDeRattachement": null,
        "valElec": "thomas.portes@assemblee-nationale.fr"
      },
      {
        "@xsi:type": "AdresseSiteWeb_Type",
        "uid": "AD799117",
        "type": "22",
        "typeLibelle": "Site internet",
        "poids": null,
        "adresseDeRattachement": null,
        "valElec": "thomasportes93.com"
      },
      {
        "@xsi:type": "AdresseSiteWeb_Type",
        "uid": "AD799207",
        "type": "25",
        "typeLibelle": "Facebook",
        "poids": null,
        "adresseDeRattachement": null,
        "valElec": "thomas portes"
      },
      {
        "@xsi:type": "AdresseSiteWeb_Type",
        "uid": "AD799211",
        "type": "29",
        "typeLibelle": "Instagram",
        "poids": null,
        "adresseDeRattachement": null,
        "valElec": "Thomas Portes"
      },
      {
        "@xsi:type": "AdresseSiteWeb_Type",
        "uid": "AD799229",
        "type": "24",
        "typeLibelle": "Twitter",
        "poids": null,
        "adresseDeRattachement": null,
        "valElec": "@Portes_Thomas"
      },
      {
        "@xsi:type": "AdressePostale_Type",
        "uid": "AD824369",
        "type": "2",
        "typeLibelle": "Adresse publiée de circonscription",
        "poids": "2",
        "adresseDeRattachement": null,
        "intitule": null,
        "numeroRue": "12",
        "nomRue": "Place Georges Pompidou",
        "complementAdresse": null,
        "codePostal": "93160",
        "ville": "Noisy-le-Grand"
      }
    ]
  },
  "mandats": {
    "mandat": [
      {
        "@xsi:type": "MandatSimple_Type",
        "uid": "PM845595",
        "acteurRef": "PA796062",
        "legislature": "17",
        "typeOrgane": "GP",
        "dateDebut": "2024-07-19",
        "datePublication": "2024-07-19",
        "dateFin": null,
        "preseance": "20",
        "nominPrincipale": "1",
        "infosQualite": {
          "codeQualite": "Membre",
          "libQualite": "Membre du",
          "libQualiteSex": "Membre du"
        },
        "organes": {
          "organeRef": "PO845413"
        }
      },
      {
        "@xsi:type": "MandatSimple_Type",
        "uid": "PM846288",
        "acteurRef": "PA796062",
        "legislature": "17",
        "typeOrgane": "COMPER",
        "dateDebut": "2024-07-20",
        "datePublication": "2024-07-20",
        "dateFin": null,
        "preseance": "32",
        "nominPrincipale": "1",
        "infosQualite": {
          "codeQualite": "Membre",
          "libQualite": "Membre",
          "libQualiteSex": "Membre"
        },
        "organes": {
          "organeRef": "PO59051"
        }
      },
      {
        "@xsi:type": "MandatParlementaire_type",
        "uid": "PM843668",
        "acteurRef": "PA796062",
        "legislature": "17",
        "typeOrgane": "ASSEMBLEE",
        "dateDebut": "2024-07-07",
        "datePublication": null,
        "dateFin": null,
        "preseance": "50",
        "nominPrincipale": "1",
        "infosQualite": {
          "codeQualite": "membre",
          "libQualite": "membre",
          "libQualiteSex": "membre"
        },
        "organes": {
          "organeRef": "PO838901"
        },
        "suppleants": {
          "suppleant": {
            "dateDebut": "2024-07-07",
            "dateFin": null,
            "suppleantRef": "PA842151"
          }
        },
        "chambre": null,
        "election": {
          "lieu": {
            "region": "Ile-de-France",
            "regionType": "Métropolitain",
            "departement": "Seine-Saint-Denis",
            "numDepartement": "93",
            "numCirco": "3"
          },
          "causeMandat": "élections générales",
          "refCirconscription": "PO840055"
        },
        "mandature": {
          "datePriseFonction": "2024-07-08",
          "causeFin": null,
          "premiereElection": "1",
          "placeHemicycle": "502",
          "mandatRemplaceRef": null
        },
        "collaborateurs": {
          "collaborateur": [
            {
              "qualite": "Mme",
              "prenom": "Sophie",
              "nom": "Perchellet",
              "dateDebut": null,
              "dateFin": null
            },
            {
              "qualite": "Mme",
              "prenom": "Aziza",
              "nom": "Nouioua",
              "dateDebut": null,
              "dateFin": null
            },
            {
              "qualite": "Mme",
              "prenom": "Khady",
              "nom": "Thiam",
              "dateDebut": null,
              "dateFin": null
            },
            {
              "qualite": "Mme",
              "prenom": "Léa",
              "nom": "Frydman",
              "dateDebut": null,
              "dateFin": null
            }
          ]
        }
      }
    ]
  }
}